flake8_function_order/__init__.py
flake8_function_order/checker.py
flake8_function_order/model_parts_info.py
flake8_function_order/ordering_errors.py
tests/__init__.py
tests/test_function_order.py
flake8_function_order-0.0.5.dist-info/LICENSE
flake8_function_order-0.0.5.dist-info/METADATA
flake8_function_order-0.0.5.dist-info/WHEEL
flake8_function_order-0.0.5.dist-info/entry_points.txt
flake8_function_order-0.0.5.dist-info/top_level.txt
flake8_function_order-0.0.5.dist-info/RECORD
