Metadata-Version: 2.1
Name: flake8-function-order
Version: 0.0.5
Summary: flake8 extension that checks function order within a class
Home-page: https://github.com/TylerYep/flake8-function-order
Author: Tyler Yep
Author-email: tyep@cs.stanford.edu
License: MIT
Keywords: flake8
Platform: UNKNOWN
Classifier: Environment :: Console
Classifier: Framework :: Flake8
Classifier: License :: OSI Approved :: MIT License
Classifier: Operating System :: OS Independent
Classifier: Programming Language :: Python
Classifier: Programming Language :: Python :: 3
Classifier: Programming Language :: Python :: 3 :: Only
Classifier: Programming Language :: Python :: 3.6
Classifier: Programming Language :: Python :: 3.7
Classifier: Programming Language :: Python :: 3.8
Classifier: Programming Language :: Python :: 3.9
Classifier: Topic :: Software Development :: Documentation
Classifier: Topic :: Software Development :: Libraries :: Python Modules
Classifier: Topic :: Software Development :: Quality Assurance
Requires-Python: >=3.6
Requires-Dist: flake8
Requires-Dist: setuptools
